array_format_optimizer.py
borsa_client.py
borsa_mcp_server.py
borsa_models.py
compact_json_optimizer.py
fon_mevzuat_kisa.py
token_optimizer.py
models/__init__.py
models/base.py
models/btcturk_models.py
models/calendar_models.py
models/coinbase_models.py
models/dovizcom_models.py
models/kap_models.py
models/mynet_models.py
models/regulation_models.py
models/tcmb_models.py
models/tefas_models.py
models/yfinance_models.py
mseep_borsa_mcp-0.7.1.dist-info/licenses/LICENSE
providers/__init__.py
providers/btcturk_provider.py
providers/coinbase_provider.py
providers/dovizcom_auth.py
providers/dovizcom_calendar_provider.py
providers/dovizcom_provider.py
providers/kap_provider.py
providers/mynet_provider.py
providers/tcmb_provider.py
providers/tefas_provider.py
providers/yfinance_provider.py
mseep_borsa_mcp-0.7.1.dist-info/METADATA
mseep_borsa_mcp-0.7.1.dist-info/WHEEL
mseep_borsa_mcp-0.7.1.dist-info/entry_points.txt
mseep_borsa_mcp-0.7.1.dist-info/top_level.txt
mseep_borsa_mcp-0.7.1.dist-info/RECORD
